textkey_extractor-0.1.0.dist-info/licenses/License
textkeyx_extractor/__init__.py
textkeyx_extractor/rake_extractor.py
textkey_extractor-0.1.0.dist-info/METADATA
textkey_extractor-0.1.0.dist-info/WHEEL
textkey_extractor-0.1.0.dist-info/top_level.txt
textkey_extractor-0.1.0.dist-info/RECORD
