Metadata-Version: 2.4
Name: textkey-extractor
Version: 0.1.0
Summary: A lightweight RAKE-style keyword extraction tool in pure Python.
Author-email: Devansh Patel <devansh.hdp@gmail.com>
License: MIT License
Requires-Python: >=3.7
License-File: License
Requires-Dist: numpy
Dynamic: license-file
